environment_backups/__init__.py
environment_backups/_experimental/__init__.py
environment_backups/_experimental/async_rich_progress_bar.py
environment_backups/_experimental/async_tqdm.py
environment_backups/_experimental/async_zipping.py
environment_backups/_experimental/display.py
environment_backups/_experimental/spinners.py
environment_backups/backups/__init__.py
environment_backups/backups/backups.py
environment_backups/backups/cli_commands.py
environment_backups/backups/projects.py
environment_backups/cli.py
environment_backups/compression.py
environment_backups/config/__init__.py
environment_backups/config/cli_commands.py
environment_backups/config/configuration.py
environment_backups/config/schemas.py
environment_backups/constants.py
environment_backups/exceptions.py
environment_backups/zipper.py
environment_backups-1.5.3.dist-info/METADATA
environment_backups-1.5.3.dist-info/WHEEL
environment_backups-1.5.3.dist-info/entry_points.txt
environment_backups-1.5.3.dist-info/RECORD
