Metadata-Version: 2.1
Name: environment-backups
Version: 1.5.3
Summary: CLI Application to backup environment variables.
Home-page: https://github.com/luiscberrocal/environment-backups
Author: Luis C. Berrocal
Author-email: luis.berrocal.1942@gmail.com
Requires-Python: >=3.10,<3.13
Classifier: Development Status :: 5 - Production/Stable
Classifier: Environment :: Console
Classifier: Intended Audience :: Developers
Classifier: Natural Language :: English
Classifier: Operating System :: POSIX :: Linux
Classifier: Programming Language :: Python :: 3
Classifier: Programming Language :: Python :: 3.10
Classifier: Programming Language :: Python :: 3.11
Classifier: Programming Language :: Python :: 3.12
Requires-Dist: click (>=8.1.3,<9.0.0)
Requires-Dist: deprecated (>=1.2.14,<2.0.0)
Requires-Dist: gdrive-pydantic-wrapper (>=0.2.6,<0.3.0)
Requires-Dist: pydantic (>=2.4.2,<3.0.0)
Requires-Dist: pyzipper (>=0.3.6,<0.4.0)
Requires-Dist: rich (>=13.4.1,<14.0.0)
Requires-Dist: simple-backups (>=0.3.2,<0.4.0)
Requires-Dist: toml (>=0.10.2,<0.11.0)
